pyxlsb2/__init__.py
pyxlsb2/cell.py
pyxlsb2/cellreference.py
pyxlsb2/datareader.py
pyxlsb2/formula.py
pyxlsb2/ptgs.py
pyxlsb2/recordreader.py
pyxlsb2/records.py
pyxlsb2/recordtypes.py
pyxlsb2/row.py
pyxlsb2/stringtable.py
pyxlsb2/styles.py
pyxlsb2/tokenreader.py
pyxlsb2/util.py
pyxlsb2/workbook.py
pyxlsb2/worksheet.py
pyxlsb2/xlsbpackage.py
pyxlsb2-0.0.9.dist-info/LICENSE
pyxlsb2-0.0.9.dist-info/LICENSE_pyxlsb
pyxlsb2-0.0.9.dist-info/METADATA
pyxlsb2-0.0.9.dist-info/WHEEL
pyxlsb2-0.0.9.dist-info/top_level.txt
pyxlsb2-0.0.9.dist-info/RECORD
