Metadata-Version: 2.1
Name: pyxlsb2
Version: 0.0.9
Summary: Excel 2007+ Binary Workbook (xlsb) parser
Home-page: https://github.com/DissectMalware/pyxlsb2
Author: Amirreza Niakanlahiji
Author-email: aniak2@uis.edu
License: Apache License 2.0
Platform: UNKNOWN
Classifier: Development Status :: 5 - Production/Stable
Classifier: License :: OSI Approved :: Apache Software License
Classifier: Programming Language :: Python :: 2
Classifier: Programming Language :: Python :: 2.7
Classifier: Programming Language :: Python :: 3
Classifier: Programming Language :: Python :: 3.5
Classifier: Programming Language :: Python :: 3.6
Classifier: Programming Language :: Python :: 3.7
Classifier: Programming Language :: Python :: 3.8
License-File: LICENSE
License-File: LICENSE_pyxlsb
